pystv/__init__.py
pystv/cli.py
pystv/pystv.py
pystv-0.0.5.dist-info/LICENSE
pystv-0.0.5.dist-info/METADATA
pystv-0.0.5.dist-info/WHEEL
pystv-0.0.5.dist-info/entry_points.txt
pystv-0.0.5.dist-info/top_level.txt
pystv-0.0.5.dist-info/RECORD
