Metadata-Version: 2.1
Name: pystv
Version: 0.0.5
Summary: "Python API for adjudicating single transferable vote elections"
Home-page: https://github.com/chrisroat/pystv
Author: Chris Roat
Author-email: chris.roat@gmail.com
License: GNU General Public License v3
Project-URL: Bug Tracker, https://github.com/chrisroat/pystv/issues
Platform: UNKNOWN
Classifier: Development Status :: 2 - Pre-Alpha
Classifier: Intended Audience :: Developers
Classifier: License :: OSI Approved :: GNU General Public License v3 (GPLv3)
Classifier: Natural Language :: English
Classifier: Programming Language :: Python :: 3
Classifier: Programming Language :: Python :: 3.7
Classifier: Programming Language :: Python :: 3.8
Classifier: Operating System :: OS Independent
Requires-Python: >=3.7
Requires-Dist: click (==8.0.4)
